snowflake/sqlalchemy/__init__.py
snowflake/sqlalchemy/_constants.py
snowflake/sqlalchemy/base.py
snowflake/sqlalchemy/compat.py
snowflake/sqlalchemy/custom_commands.py
snowflake/sqlalchemy/custom_types.py
snowflake/sqlalchemy/exc.py
snowflake/sqlalchemy/functions.py
snowflake/sqlalchemy/provision.py
snowflake/sqlalchemy/requirements.py
snowflake/sqlalchemy/snowdialect.py
snowflake/sqlalchemy/util.py
snowflake/sqlalchemy/version.py
snowflake/sqlalchemy/parser/custom_type_parser.py
snowflake/sqlalchemy/sql/__init__.py
snowflake/sqlalchemy/sql/custom_schema/__init__.py
snowflake/sqlalchemy/sql/custom_schema/clustered_table.py
snowflake/sqlalchemy/sql/custom_schema/custom_table_base.py
snowflake/sqlalchemy/sql/custom_schema/custom_table_prefix.py
snowflake/sqlalchemy/sql/custom_schema/dynamic_table.py
snowflake/sqlalchemy/sql/custom_schema/hybrid_table.py
snowflake/sqlalchemy/sql/custom_schema/iceberg_table.py
snowflake/sqlalchemy/sql/custom_schema/snowflake_table.py
snowflake/sqlalchemy/sql/custom_schema/table_from_query.py
snowflake/sqlalchemy/sql/custom_schema/options/__init__.py
snowflake/sqlalchemy/sql/custom_schema/options/as_query_option.py
snowflake/sqlalchemy/sql/custom_schema/options/cluster_by_option.py
snowflake/sqlalchemy/sql/custom_schema/options/identifier_option.py
snowflake/sqlalchemy/sql/custom_schema/options/invalid_table_option.py
snowflake/sqlalchemy/sql/custom_schema/options/keyword_option.py
snowflake/sqlalchemy/sql/custom_schema/options/keywords.py
snowflake/sqlalchemy/sql/custom_schema/options/literal_option.py
snowflake/sqlalchemy/sql/custom_schema/options/table_option.py
snowflake/sqlalchemy/sql/custom_schema/options/target_lag_option.py
snowflake_sqlalchemy-1.7.5.dist-info/METADATA
snowflake_sqlalchemy-1.7.5.dist-info/WHEEL
snowflake_sqlalchemy-1.7.5.dist-info/entry_points.txt
snowflake_sqlalchemy-1.7.5.dist-info/licenses/LICENSE.txt
snowflake_sqlalchemy-1.7.5.dist-info/RECORD
