Metadata-Version: 2.4
Name: snowflake-sqlalchemy
Version: 1.7.5
Summary: Snowflake SQLAlchemy Dialect
Project-URL: Changelog, https://github.com/snowflakedb/snowflake-sqlalchemy/blob/main/DESCRIPTION.md
Project-URL: Documentation, https://docs.snowflake.com/en/user-guide/sqlalchemy.html
Project-URL: Homepage, https://www.snowflake.com/
Project-URL: Issues, https://github.com/snowflakedb/snowflake-sqlalchemy/issues
Project-URL: Source, https://github.com/snowflakedb/snowflake-sqlalchemy
Author-email: "Snowflake Inc." <triage-snowpark-python-api-dl@snowflake.com>
License-Expression: Apache-2.0
License-File: LICENSE.txt
Keywords: Snowflake,analytics,cloud,database,db,warehouse
Classifier: Development Status :: 5 - Production/Stable
Classifier: Environment :: Console
Classifier: Environment :: Other Environment
Classifier: Intended Audience :: Developers
Classifier: Intended Audience :: Education
Classifier: Intended Audience :: Information Technology
Classifier: Intended Audience :: System Administrators
Classifier: License :: OSI Approved :: Apache Software License
Classifier: Operating System :: OS Independent
Classifier: Programming Language :: Python :: 3
Classifier: Programming Language :: Python :: 3 :: Only
Classifier: Programming Language :: Python :: 3.8
Classifier: Programming Language :: Python :: 3.9
Classifier: Programming Language :: Python :: 3.10
Classifier: Programming Language :: Python :: 3.11
Classifier: Programming Language :: Python :: 3.12
Classifier: Programming Language :: SQL
Classifier: Topic :: Database
Classifier: Topic :: Scientific/Engineering :: Information Analysis
Classifier: Topic :: Software Development
Classifier: Topic :: Software Development :: Libraries
Classifier: Topic :: Software Development :: Libraries :: Application Frameworks
Classifier: Topic :: Software Development :: Libraries :: Python Modules
Requires-Python: >=3.8
Requires-Dist: snowflake-connector-python<4.0.0
Requires-Dist: sqlalchemy>=1.4.19
Provides-Extra: development
Requires-Dist: mock; extra == 'development'
Requires-Dist: numpy; extra == 'development'
Requires-Dist: pre-commit; extra == 'development'
Requires-Dist: pytest; extra == 'development'
Requires-Dist: pytest-cov; extra == 'development'
Requires-Dist: pytest-rerunfailures; extra == 'development'
Requires-Dist: pytest-timeout; extra == 'development'
Requires-Dist: pytz; extra == 'development'
Requires-Dist: setuptools; extra == 'development'
Requires-Dist: syrupy==4.6.1; extra == 'development'
Provides-Extra: pandas
Requires-Dist: snowflake-connector-python[pandas]; extra == 'pandas'
